{
  "schemaVersion": 1,
  "cron": "skeletonswap-lp_data",
  "capturedAt": "2026-06-10T23:45:24.377Z",
  "capturedAtUnix": 1781135124377,
  "runId": "ss-20260610234524",
  "runMode": "daily",
  "currentEpoch": 189,
  "status": "ok",
  "stats": {
    "poolsProcessed": 34,
    "poolsPriced": 29,
    "poolsUnpriced": 5,
    "poolsChainFailed": 0,
    "tvlSumUsd": 515645.24,
    "fileWritten": "day-3.csv"
  },
  "dataFingerprint": "a700ce2bfff6",
  "previousFingerprint": "50ab6d222589",
  "dataFreshness": "fresh",
  "consecutiveStuckRuns": 0,
  "next_expected_run_at": "2026-06-11T23:45:24.377Z"
}