{
  "schemaVersion": 1,
  "cron": "skeletonswap-lp_data",
  "capturedAt": "2026-06-08T00:05:19.580Z",
  "capturedAtUnix": 1780877119580,
  "runId": "ss-20260608000519",
  "runMode": "weekly",
  "currentEpoch": 189,
  "status": "ok",
  "stats": {
    "poolsProcessed": 34,
    "poolsPriced": null,
    "poolsUnpriced": null,
    "poolsChainFailed": null,
    "tvlSumUsd": null,
    "fileWritten": "2026-epoch-189.csv"
  },
  "dataFingerprint": null,
  "previousFingerprint": null,
  "dataFreshness": null,
  "consecutiveStuckRuns": 0,
  "next_expected_run_at": "2026-06-15T00:05:19.580Z"
}